consuela/__init__.py
consuela/core.py
consuela-0.1.0.dist-info/WHEEL
consuela-0.1.0.dist-info/METADATA
consuela-0.1.0.dist-info/RECORD
