Metadata-Version: 2.1
Name: consuela
Version: 0.1.0
Summary: Format and linters pack
License: MIT
Author: Nick Sablukov
Author-email: dessanndes@gmail.com
Requires-Python: >=3.6
Classifier: License :: OSI Approved :: MIT License
Classifier: Programming Language :: Python :: 3
Classifier: Programming Language :: Python :: 3.6
Classifier: Programming Language :: Python :: 3.7
Classifier: Programming Language :: Python :: 3.8
